djangorestframework_date_archive-0.3.0.dist-info/METADATA
djangorestframework_date_archive-0.3.0.dist-info/RECORD
djangorestframework_date_archive-0.3.0.dist-info/WHEEL
djangorestframework_date_archive-0.3.0.dist-info/top_level.txt
rest_framework_date_archive/__init__.py
rest_framework_date_archive/querysets.py
rest_framework_date_archive/routers.py
rest_framework_date_archive/views.py
